LICENSE
README.md
setup.py
guiblox/__init__.py
guiblox/__main__.py
guiblox/buttonCol.py
guiblox/buttonRow.py
guiblox/entryCol.py
guiblox/listWindow.py
guiblox/theme.py
guiblox.egg-info/PKG-INFO
guiblox.egg-info/SOURCES.txt
guiblox.egg-info/dependency_links.txt
guiblox.egg-info/not-zip-safe
guiblox.egg-info/top_level.txt
test/test_guiblox_import.py
test/test_project_import.py