Metadata-Version: 2.1
Name: guiblox
Version: 2022.1.18
Summary: GUI Widgets in Frames
Home-page: https://github.com/mclim9/guiblox
Author: Martin C Lim
Author-email: trabin9@gmail.com
License: MIT Open Source
Keywords: tkinter
Platform: UNKNOWN
Classifier: Development Status :: 3 - Alpha
Classifier: License :: OSI Approved :: MIT License
Classifier: Intended Audience :: Developers
Classifier: Programming Language :: Python :: 3.7
Classifier: Topic :: Scientific/Engineering :: Electronic Design Automation (EDA)
License-File: LICENSE
